{
  "type": "minecraft:chest",
  "pools": [
    {
      "bonus_rolls": 0.0,
      "entries": [
        {
          "type": "minecraft:item",
          "functions": [
            {
              "add": false,
              "count": {
                "type": "minecraft:uniform",
                "max": 6.0,
                "min": 1.0
              },
              "function": "minecraft:set_count"
            }
          ],
          "name": "minecraft:lapis_lazuli",
          "weight": 50
        },
        {
          "type": "minecraft:item",
          "functions": [
            {
              "add": false,
              "count": {
                "type": "minecraft:uniform",
                "max": 4.0,
                "min": 1.0
              },
              "function": "minecraft:set_count"
            }
          ],
          "name": "minecraft:emerald",
          "weight": 30
        },
        {
          "type": "minecraft:item",
          "functions": [
            {
              "add": false,
              "count": {
                "type": "minecraft:uniform",
                "max": 2.0,
                "min": 1.0
              },
              "function": "minecraft:set_count"
            }
          ],
          "name": "minecraft:gold_block",
          "weight": 20
        },
        {
          "type": "minecraft:item",
          "functions": [
            {
              "add": false,
              "count": {
                "type": "minecraft:uniform",
                "max": 4.0,
                "min": 1.0
              },
              "function": "minecraft:set_count"
            }
          ],
          "name": "minecraft:diamond",
          "weight": 10
        },
        {
          "type": "minecraft:item",
          "functions": [
            {
              "add": false,
              "count": {
                "type": "minecraft:uniform",
                "max": 2.0,
                "min": 1.0
              },
              "function": "minecraft:set_count"
            }
          ],
          "name": "minecraft:netherite_scrap"
        }
      ],
      "rolls": {
        "type": "minecraft:uniform",
        "max": 5.0,
        "min": 2.0
      }
    }
  ]
}