{
  "parent": "minecraft:recipes/root",
  "rewards": {
    "recipes": [
      "crafted_cuisine:dark_oak_wood_from_rebark"
    ]
  },
  "criteria": {
    "has_dark_oak_bark": {
      "trigger": "minecraft:inventory_changed",
      "conditions": {
        "items": [
          {
            "items": [
              "crafted_cuisine:dark_oak_bark"
            ]
          }
        ]
      }
    },
    "has_the_recipe": {
      "trigger": "minecraft:recipe_unlocked",
      "conditions": {
        "recipe": "crafted_cuisine:dark_oak_wood_from_rebark"
      }
    }
  },
  "requirements": [
    [
      "has_dark_oak_bark",
      "has_the_recipe"
    ]
  ]
}